jarbin_toolkit_error/__init__.py
jarbin_toolkit_error/error.py
jarbin_toolkit_error-0.1.0.0.dist-info/licenses/LICENSE
jarbin_toolkit_error-0.1.0.0.dist-info/METADATA
jarbin_toolkit_error-0.1.0.0.dist-info/WHEEL
jarbin_toolkit_error-0.1.0.0.dist-info/top_level.txt
jarbin_toolkit_error-0.1.0.0.dist-info/RECORD
