Metadata-Version: 2.4
Name: jarbin-toolkit-error
Version: 0.1.0.0
Summary: Error tools (Formated error / better visual / etc...)
Author-email: Nathan Jarjarbin <nathan.amaraggi@epitech.eu>
License-Expression: GPL-3.0-or-later
Project-URL: Homepage, https://jarjarbin06.github.io/jarbin-toolkit/
Project-URL: Repository, https://github.com/Jarjarbin06/jarbin-toolkit/
Project-URL: Issues, https://github.com/Jarjarbin06/jarbin-toolkit/issues/
Classifier: Programming Language :: Python :: 3.13
Classifier: Operating System :: OS Independent
Classifier: Environment :: Console
Classifier: Development Status :: 3 - Alpha
Classifier: Intended Audience :: Developers
Classifier: Topic :: Software Development :: Libraries
Classifier: Topic :: Terminals
Classifier: Topic :: Utilities
Requires-Python: >=3.11
License-File: LICENSE
Requires-Dist: datetime
Dynamic: license-file
